[
  {
    "nombre": "Saku especial roll (Uramaki)",
    "categoria": "Sakura rolls especiales",
    "precioNormal": "",
    "precioOferta": "",
    "descripcion": [
      "Relleno de Camarón Apanado, Queso Crema y Palta",
      "Envoltura de Ciboulette",
      "Topping de Tartaro Nikkei de atún",
      "Bañado en Salsa de Masago"
    ],
    "disponible": ""
  },
  {
    "nombre": "Dinamita roll (Uramaki)",
    "categoria": "Sakura rolls especiales",
    "precioNormal": "",
    "precioOferta": "",
    "descripcion": [
      "Relleno de Camarón Apanado, Queso Crema y Ciboulette",
      "Envoltura mitad Palta mitad Salmón",
      "Topping de Kanikama especial",
      "Bañado en salsa de masago",
      "Coronado con sesamo"
    ],
    "disponible": ""
  },
  {
    "nombre": "Yaki roll (Tempura)",
    "categoria": "Sakura rolls especiales",
    "precioNormal": "",
    "precioOferta": "",
    "descripcion": [
      "Relleno de Kanikama, Queso Crema y Ciboulette",
      "Topping de Wakame",
      "Bañado en Salsa de Masago y Salsa Teriyaki",
      "Coronado con Kanikama Crunsh"
    ],
    "disponible": ""
  },
  {
    "nombre": "Acevichado roll (Uramaki)",
    "categoria": "Sakura rolls especiales",
    "precioNormal": "",
    "precioOferta": "",
    "descripcion": [
      "Relleno de Camarón Apanado, queso crema y Kanikama",
      "Envoltura de Palta",
      "Topping de ceviche",
      "Bañado en Salsa Acevichada",
      "Coronado con Togarashi y cancha"
    ],
    "disponible": ""
  },
  {
    "nombre": "Spicy roll (Uramaki)",
    "categoria": "Sakura rolls especiales",
    "precioNormal": "",
    "precioOferta": "",
    "descripcion": [
      "Relleno de Salmón, Queso Crema y Palta",
      "Envuelto en Sesamo",
      "Topping de Kanikama especial",
      "Bañado en Salsa de Rocoto",
      "Coronado con Togarashi"
    ],
    "disponible": ""
  },
  {
    "nombre": "Platano roll (Uramaki)",
    "categoria": "Sakura rolls especiales",
    "precioNormal": "",
    "precioOferta": "",
    "descripcion": [
      "Relleno de Camarón Apanado, Queso Crema y Cebollín",
      "Envuelto en Plátano",
      "Topping de Kanikama especial",
      "Bañado en Salsa Teriyaki",
      "Coronado con ciboulette."
    ],
    "disponible": ""
  },
  {
    "nombre": "Tokio roll (Futomaki apanado)",
    "categoria": "Sakura rolls especiales",
    "precioNormal": "",
    "precioOferta": "",
    "descripcion": [
      "Relleno de Kanikama apanado, Camarón Apanado, Queso Crema, Cebollín",
      "Topping de ensalada neptuno",
      "Bañado con Salsa Teriyaki",
      "Coronado con masago"
    ],
    "disponible": ""
  },
  {
    "nombre": "Tropical roll (Uramaki)",
    "categoria": "Sakura rolls especiales",
    "precioNormal": "",
    "precioOferta": "",
    "descripcion": [
      "Relleno de Camarón Apanado, Kanikama, Queso Crema",
      "Envoltura de Palta",
      "Topping de Chalaca (cebolla morada, ciboulette, rocoto, ají amarillo y cilantro)",
      "Coronado con Kanikama Crunsh",
      "Salsa de Leche de Tigre de Maracuyá en la base del plato"
    ],
    "disponible": ""
  },
  {
    "nombre": "Fugi roll (Uramaki)",
    "categoria": "Sakura rolls especiales",
    "precioNormal": "",
    "precioOferta": "",
    "descripcion": [
      "Relleno de Kanikama apanado, Palta, Queso Crema",
      "Envuelto en Sesamo",
      "Topping de Camarón Apanado",
      "Bañado en Salsa Fugi",
      "Coronado con ciboulette."
    ],
    "disponible": ""
  },
  {
    "nombre": "Dako roll (Sin arroz)",
    "categoria": "Sakura rolls especiales",
    "precioNormal": "",
    "precioOferta": "",
    "descripcion": [
      "Relleno de Salmón, Camarón Apanado, Kanikama apanado, Queso Crema palta y ciboulette",
      "Topping de Kanikama especial",
      "Bañado en salsa de masago y Salsa Angila",
      "Coronado con sesamo"
    ],
    "disponible": ""
  },
  {
    "nombre": "Super Ligth roll (Sin arroz)",
    "categoria": "Sakura rolls especiales",
    "precioNormal": "",
    "precioOferta": "",
    "descripcion": [
      "Relleno de Salmón, Camarón Apanado, Kanikama apanado, Queso Crema, Palta y Ciboulette",
      "Envoltura de Salmón",
      "Salsa acevichada",
      "Coronado con masago."
    ],
    "disponible": ""
  },
  {
    "nombre": "Saku especial roll (Uramaki)",
    "categoria": "Sakura rolls especiales",
    "precioNormal": "",
    "precioOferta": "",
    "descripcion": "",
    "disponible": ""
  },
  {
    "nombre": "Saku especial roll (Uramaki)",
    "categoria": "Sakura rolls especiales",
    "precioNormal": "",
    "precioOferta": "",
    "descripcion": "",
    "disponible": ""
  },
  {
    "nombre": "Saku especial roll (Uramaki)",
    "categoria": "Sakura rolls especiales",
    "precioNormal": "",
    "precioOferta": "",
    "descripcion": "",
    "disponible": ""
  },
  {
    "nombre": "Saku especial roll (Uramaki)",
    "categoria": "Sakura rolls especiales",
    "precioNormal": "",
    "precioOferta": "",
    "descripcion": "",
    "disponible": ""
  },
  {
    "nombre": "Saku especial roll (Uramaki)",
    "categoria": "Sakura rolls especiales",
    "precioNormal": "",
    "precioOferta": "",
    "descripcion": "",
    "disponible": ""
  },
  {
    "nombre": "Saku especial roll (Uramaki)",
    "categoria": "Sakura rolls especiales",
    "precioNormal": "",
    "precioOferta": "",
    "descripcion": "",
    "disponible": ""
  },
  {
    "nombre": "Saku especial roll (Uramaki)",
    "categoria": "Sakura rolls especiales",
    "precioNormal": "",
    "precioOferta": "",
    "descripcion": "",
    "disponible": ""
  },
  {
    "nombre": "Saku especial roll (Uramaki)",
    "categoria": "Sakura rolls especiales",
    "precioNormal": "",
    "precioOferta": "",
    "descripcion": "",
    "disponible": ""
  },
  {
    "nombre": "Saku especial roll (Uramaki)",
    "categoria": "Sakura rolls especiales",
    "precioNormal": "",
    "precioOferta": "",
    "descripcion": "",
    "disponible": ""
  },
  {
    "nombre": "Saku especial roll (Uramaki)",
    "categoria": "Sakura rolls especiales",
    "precioNormal": "",
    "precioOferta": "",
    "descripcion": "",
    "disponible": ""
  },
  {
    "nombre": "Saku especial roll (Uramaki)",
    "categoria": "Sakura rolls especiales",
    "precioNormal": "",
    "precioOferta": "",
    "descripcion": "",
    "disponible": ""
  },
  {
    "nombre": "Saku especial roll (Uramaki)",
    "categoria": "Sakura rolls especiales",
    "precioNormal": "",
    "precioOferta": "",
    "descripcion": "",
    "disponible": ""
  }
]
